edgee/__init__.py
edgee/py.typed
edgee-1.0.0.dist-info/METADATA
edgee-1.0.0.dist-info/WHEEL
edgee-1.0.0.dist-info/licenses/LICENSE
edgee-1.0.0.dist-info/RECORD
