Metadata-Version: 2.4
Name: edgee
Version: 1.0.0
Summary: Lightweight Python SDK for Edgee AI Gateway
Project-URL: Homepage, https://github.com/edgee-cloud/python-sdk
Project-URL: Repository, https://github.com/edgee-cloud/python-sdk
Author-email: Edgee <support@edgee.cloud>
License-Expression: Apache-2.0
License-File: LICENSE
Keywords: ai,anthropic,gateway,llm,openai
Classifier: Development Status :: 4 - Beta
Classifier: Intended Audience :: Developers
Classifier: License :: OSI Approved :: Apache Software License
Classifier: Programming Language :: Python :: 3
Classifier: Programming Language :: Python :: 3.10
Classifier: Programming Language :: Python :: 3.11
Classifier: Programming Language :: Python :: 3.12
Classifier: Topic :: Software Development :: Libraries :: Python Modules
Requires-Python: >=3.10
Provides-Extra: dev
Requires-Dist: pytest>=8.0.0; extra == 'dev'
Requires-Dist: ruff>=0.8.0; extra == 'dev'
